runningbox_api_python/__init__.py
runningbox_api_python/client.py
runningbox_api_python/errors.py
runningbox_api_python/utils.py
runningbox_api_python/version.py
runningbox_api_python/constants/__init__.py
runningbox_api_python/constants/error_codes.py
runningbox_api_python/constants/services.py
runningbox_api_python/constants/stages.py
runningbox_api_python/constants/status_codes.py
runningbox_api_python/constants/urls.py
runningbox_api_python/resources/__init__.py
runningbox_api_python/resources/base.py
runningbox_api_python/resources/data_structures.py
runningbox_api_python/resources/order.py
runningbox_api_python-1.0.0.dist-info/LICENSE
runningbox_api_python-1.0.0.dist-info/METADATA
runningbox_api_python-1.0.0.dist-info/WHEEL
runningbox_api_python-1.0.0.dist-info/top_level.txt
runningbox_api_python-1.0.0.dist-info/RECORD
