Metadata-Version: 2.1
Name: runningbox-api-python
Version: 1.0.0
Summary: Running Box API Python
Home-page: https://gitlab.com/softbutterfly/runningbox-api-python
Author: SoftButterfly Development Team
Author-email: SoftButterfly Development Team <dev@softbutterfly.io>
License: UNKNOWN
Download-URL: https://gitlab.com/softbutterfly/runningbox-api-python/-/archive/1.0.0/runningbox-api-python-1.0.0.tar.gz
Keywords: Softbutterfly,Running box,Running box API
Platform: UNKNOWN
Classifier: Development Status :: 5 - Production/Stable
Classifier: Intended Audience :: Developers
Classifier: License :: OSI Approved :: MIT License
Classifier: Natural Language :: English
Classifier: Programming Language :: Python :: 3.7
Classifier: Topic :: Software Development :: Libraries :: Python Modules
Requires: requests
Requires-Dist: requests
